setup.py
webassets_traceur/__init__.py
webassets_traceur/_version.py
webassets_traceur/filters.py
webassets_traceur.egg-info/PKG-INFO
webassets_traceur.egg-info/SOURCES.txt
webassets_traceur.egg-info/dependency_links.txt
webassets_traceur.egg-info/requires.txt
webassets_traceur.egg-info/top_level.txt