Metadata-Version: 1.1
Name: webassets-traceur
Version: 0.1.0
Summary: An additional webassets filter to compile ES6 to ES5 using traceur.
Home-page: http://github.com/concordusapps/webassets-traceur
Author: Concordus Applications
Author-email: support@concordusapps.com
License: UNKNOWN
Platform: UNKNOWN
Classifier: Development Status :: 3 - Alpha
Classifier: Framework :: Flask
Classifier: Intended Audience :: Developers
Classifier: Intended Audience :: System Administrators
Classifier: License :: OSI Approved :: MIT License
Classifier: Operating System :: OS Independent
Classifier: Programming Language :: Python :: 3.3
Classifier: Topic :: Software Development :: Libraries :: Python Modules
Classifier: Topic :: Utilities
